__init__.py
check_style.py
finglishV2.py
persion_and_english_letters.py
finglish_words-1.0.2.dist-info/METADATA
finglish_words-1.0.2.dist-info/WHEEL
finglish_words-1.0.2.dist-info/top_level.txt
finglish_words-1.0.2.dist-info/RECORD
