Metadata-Version: 2.1
Name: finglish-words
Version: 1.0.2
Summary: Fun modul for persion language people
Home-page: UNKNOWN
Author: Ahmad Dehghani
Author-email: ahd76money@gmail.com
License: MIT
Keywords: finlish,persion,bot,telegram,chat,scrapper,images,videos
Platform: UNKNOWN
